flask_skeleton/__init__.py
flask_skeleton/core.py
flask_skeleton/summary.jinja
flask_skeleton/skeleton/.flaskenv
flask_skeleton/skeleton/.gitignore
flask_skeleton/skeleton/README.md
flask_skeleton/skeleton/config.py
flask_skeleton/skeleton/requirements.txt
flask_skeleton/skeleton/wsgi.py
flask_skeleton/skeleton/app/__init__.py
flask_skeleton/skeleton/app/forms.py
flask_skeleton/skeleton/app/models.py
flask_skeleton/skeleton/app/utils.py
flask_skeleton/skeleton/app/views.py
flask_skeleton/skeleton/app/auth/__init__.py
flask_skeleton/skeleton/app/auth/forms.py
flask_skeleton/skeleton/app/auth/models.py
flask_skeleton/skeleton/app/auth/views.py
flask_skeleton/skeleton/app/static/main.css
flask_skeleton/skeleton/app/static/main.js
flask_skeleton/skeleton/app/templates/_macros.html
flask_skeleton/skeleton/app/templates/base.html
flask_skeleton/skeleton/app/templates/error.html
flask_skeleton/skeleton/app/templates/index.html
flask_skeleton/skeleton/app/templates/auth/login.html
flask_skeleton/skeleton/app/templates/auth/register.html
flask_skeleton/skeleton/tests/__init__.py
flask_skeleton/skeleton/tests/test_app.py
flask_skeleton-1.0.2.dist-info/LICENSE
flask_skeleton-1.0.2.dist-info/METADATA
flask_skeleton-1.0.2.dist-info/WHEEL
flask_skeleton-1.0.2.dist-info/entry_points.txt
flask_skeleton-1.0.2.dist-info/top_level.txt
flask_skeleton-1.0.2.dist-info/RECORD
