Metadata-Version: 2.1
Name: flask-skeleton
Version: 1.0.2
Summary: Quick start a flask app
Home-page: https://github.com/enwawerueli/flask-skeleton
Author: enwawerueli
Author-email: seaworndrift@gmail.com
License: MIT
Platform: UNKNOWN
Classifier: Programming Language :: Python :: 3
Classifier: License :: OSI Approved :: MIT License
Classifier: Operating System :: Unix
Classifier: Intended Audience :: Developers
Classifier: Framework :: Flask
Classifier: Topic :: Utilities
Classifier: Natural Language :: English
Requires-Python: >=3
License-File: LICENSE
